bucketstore.py
bucketstore-0.3.0.dist-info/LICENSE
bucketstore-0.3.0.dist-info/METADATA
bucketstore-0.3.0.dist-info/WHEEL
bucketstore-0.3.0.dist-info/RECORD
