Metadata-Version: 2.1
Name: bucketstore
Version: 0.3.0
Summary: A simple library for interacting with Amazon S3.
Home-page: https://github.com/jpetrucciani/bucketstore
Author: jacobi petrucciani
Author-email: j@cobi.dev
Requires-Python: >=3.8
Classifier: License :: OSI Approved :: MIT License
Classifier: Programming Language :: Python :: 3
Classifier: Programming Language :: Python :: 3.8
Classifier: Programming Language :: Python :: 3.9
Classifier: Programming Language :: Python :: 3.10
Classifier: Programming Language :: Python :: 3.11
Classifier: Programming Language :: Python :: 3.12
Classifier: Programming Language :: Python :: 3.13
Classifier: Programming Language :: Python :: Implementation :: CPython
Classifier: Programming Language :: Python :: Implementation :: PyPy
Requires-Dist: boto3 (>=1.20.0)
Project-URL: Repository, https://github.com/jpetrucciani/bucketstore
